machina_core_sdk/__init__.py
machina_core_sdk/main.py
machina_core_sdk/version.py
machina_sports_core_sdk-0.1.16.dist-info/METADATA
machina_sports_core_sdk-0.1.16.dist-info/WHEEL
machina_sports_core_sdk-0.1.16.dist-info/top_level.txt
machina_sports_core_sdk-0.1.16.dist-info/RECORD
