Metadata-Version: 2.1
Name: machina-sports-core-sdk
Version: 0.1.16
Summary: Machina Sports Core SDK
Author: Fernando Bombassaro Martins
Author-email: Fernando Bombassaro Martins <fernando@machina.gg>
License: MIT
Classifier: Programming Language :: Python :: 3.9
Classifier: License :: OSI Approved :: MIT License
Classifier: Operating System :: OS Independent
Requires-Python: >=3.9,<4.0
Requires-Dist: requests<3.0.0,>=2.26.0
Requires-Dist: pydantic<2.0.0,>=1.8.2
